src/__init__.py
src/config.py
src/data_models.py
src/editor.py
src/exceptions.py
src/file_access.py
src/main.py
src/mcp_schemas.py
src/search_engine.py
src/server.py
src/tools.py
src/tree_parser.py
src/utils.py
largefile-0.1.5.dist-info/METADATA
largefile-0.1.5.dist-info/WHEEL
largefile-0.1.5.dist-info/entry_points.txt
largefile-0.1.5.dist-info/RECORD
