Metadata-Version: 2.4
Name: largefile
Version: 0.1.5
Summary: MCP server for AI assistants to navigate, search, and edit large codebases, logs, and data files with semantic code analysis
Project-URL: Homepage, https://github.com/peteretelej/largefile
Project-URL: Repository, https://github.com/peteretelej/largefile.git
Project-URL: Issues, https://github.com/peteretelej/largefile/issues
Project-URL: Documentation, https://github.com/peteretelej/largefile#readme
Author-email: Peter Etelej <peter@etelej.com>
Maintainer-email: Peter Etelej <peter@etelej.com>
License: MIT
Keywords: ai-tools,code-navigation,large-files,llm,log-analysis,mcp,semantic-analysis,tree-sitter
Classifier: Development Status :: 5 - Production/Stable
Classifier: Intended Audience :: Developers
Classifier: Operating System :: OS Independent
Classifier: Programming Language :: Python :: 3
Classifier: Programming Language :: Python :: 3.10
Classifier: Programming Language :: Python :: 3.11
Classifier: Programming Language :: Python :: 3.12
Classifier: Topic :: Software Development :: Libraries :: Python Modules
Classifier: Topic :: Text Processing
Classifier: Typing :: Typed
Requires-Python: >=3.10
Requires-Dist: chardet>=5.0.0
Requires-Dist: click>=8.2.1
Requires-Dist: mcp>=1.10.1
Requires-Dist: rapidfuzz>=3.0.0
Requires-Dist: tree-sitter-go>=0.21.0
Requires-Dist: tree-sitter-javascript>=0.21.0
Requires-Dist: tree-sitter-python>=0.21.0
Requires-Dist: tree-sitter-rust>=0.21.0
Requires-Dist: tree-sitter-typescript>=0.21.0
Requires-Dist: tree-sitter>=0.21.0
